ez0th/__init__.py
ez0th/test.py
ez0th-0.2.0.dist-info/METADATA
ez0th-0.2.0.dist-info/WHEEL
ez0th-0.2.0.dist-info/top_level.txt
ez0th-0.2.0.dist-info/RECORD
