Metadata-Version: 2.1
Name: ez0th
Version: 0.2.0
Summary: Python Library for Easy Authentication and Authorization
Home-page: https://github.co.jp/
Author: bib_inf
Author-email: contact.bibinf@gmail.com
License: CC0 v1.0
Classifier: Programming Language :: Python :: 3
Classifier: License :: CC0 1.0 Universal (CC0 1.0) Public Domain Dedication
Requires-Dist: json-stock
Requires-Dist: slim-id
Requires-Dist: ezpip
Requires-Dist: sout (>=1.2.1)
Requires-Dist: relpath
